pytorch_tcn/__init__.py
pytorch_tcn/buffer.py
pytorch_tcn/condition.py
pytorch_tcn/conditional_layer.py
pytorch_tcn/conv.py
pytorch_tcn/pad.py
pytorch_tcn/tcn.py
pytorch_tcn-1.2.3.dist-info/licenses/LICENSE
pytorch_tcn-1.2.3.dist-info/METADATA
pytorch_tcn-1.2.3.dist-info/WHEEL
pytorch_tcn-1.2.3.dist-info/top_level.txt
pytorch_tcn-1.2.3.dist-info/RECORD
