Metadata-Version: 2.4
Name: pytorch-tcn
Version: 1.2.3
Summary: Pytorch TCN
Home-page: https://github.com/paul-krug/pytorch-tcn
Author: Paul Krug
License: MIT
License-File: LICENSE
Requires-Dist: torch
Requires-Dist: numpy
Dynamic: author
Dynamic: description
Dynamic: description-content-type
Dynamic: home-page
Dynamic: license
Dynamic: license-file
Dynamic: requires-dist
Dynamic: summary
